<?xml version="1.0" encoding="UTF-8"?>
<ref id="B47-molecules-25-00891">
 <label>47.</label>
 <element-citation publication-type="book">
  <person-group person-group-type="author">
   <name>
    <surname>Lowell</surname>
    <given-names>S.</given-names>
   </name>
   <name>
    <surname>Shields</surname>
    <given-names>J.E.</given-names>
   </name>
   <name>
    <surname>Thomas</surname>
    <given-names>M.A.</given-names>
   </name>
   <name>
    <surname>Thommes</surname>
    <given-names>M.</given-names>
   </name>
  </person-group>
  <source>Characterization of Porous Solids and Powders: Surface Area, Pore Size and Density</source>
  <edition>3rd ed.</edition>
  <publisher-name>Springer</publisher-name>
  <publisher-loc>Dordrecht, The Netherland</publisher-loc>
  <year>2006</year>
 </element-citation>
</ref>
