<?xml version="1.0" encoding="UTF-8"?>
<ref id="anie201914760-bib-0024">
 <label>24</label>
 <mixed-citation publication-type="journal" id="anie201914760-cit-0037">
  <string-name>
   <given-names>M.</given-names>
   <surname>Fehse</surname>
  </string-name>, 
  <string-name>
   <given-names>A.</given-names>
   <surname>Darwiche</surname>
  </string-name>, 
  <string-name>
   <given-names>M. T.</given-names>
   <surname>Sougrati</surname>
  </string-name>, 
  <string-name>
   <given-names>E. M.</given-names>
   <surname>Kelder</surname>
  </string-name>, 
  <string-name>
   <given-names>A. V.</given-names>
   <surname>Chadwick</surname>
  </string-name>, 
  <string-name>
   <given-names>M.</given-names>
   <surname>Alfredsson</surname>
  </string-name>, 
  <string-name>
   <given-names>L.</given-names>
   <surname>Monconduit</surname>
  </string-name>, 
  <string-name>
   <given-names>L.</given-names>
   <surname>Stievano</surname>
  </string-name>, 
  <source xml:lang="en">Chem. Mater.</source>
  <year>2017</year>, 
  <volume>29</volume>, 
  <fpage>10446</fpage>–
  <lpage>10454</lpage>.
 </mixed-citation>
</ref>
