<?xml version="1.0" encoding="UTF-8"?>
<supplementary-material content-type="local-data" id="MOESM4">
 <media xlink:href="12870_2021_2852_MOESM4_ESM.tif" xmlns:xlink="http://www.w3.org/1999/xlink">
  <caption>
   <p>
    <bold>Additional file 4: Figure S4.</bold> (A) Single-cell transcriptome Venn diagram shows the expression of genes between samples. (B) Proteome and metabolome combined analysis with KEGG enrichment analysis. (C) Proteome and transcriptome joint analysis with KEGG enrichment analysis. (D) Combined analysis of transcriptome and metabolome with KEGG enrichment
   </p>
  </caption>
 </media>
</supplementary-material>
