<?xml version="1.0" encoding="UTF-8"?>
<fig id="Fig3">
 <label>Fig. 3</label>
 <caption>
  <title>The results and analysis of MD simmulations in the presence of variable amounts of water.</title>
  <p>
   <bold>a</bold>–
   <bold>g</bold> p(MMA/nBA) copolymers surrounded by H
   <sub>2</sub>O molecules (
   <italic>R</italic>
   <sub>w</sub> = 0, 1:4, 1:2, 3:4, 1:1, 4:3, and 2:1); A1/A2/A3–G1/G2/G3 illustrates the results of MD simulations: A1–G1–A3–G3 are image-extracted macromolecules from MD simulations: A1–G1 are copolymer backbone, side groups, and water, A2–G2 are backbone atoms and water, and A3–G3 are backbone units.
  </p>
 </caption>
 <graphic xlink:href="41467_2020_19405_Fig3_HTML" id="d30e1206" xmlns:xlink="http://www.w3.org/1999/xlink"/>
</fig>
