<?xml version="1.0" encoding="UTF-8"?>
<ref id="advs1498-bib-0062">
 <label>62</label>
 <mixed-citation publication-type="journal" id="advs1498-cit-0125">
  <string-name>
   <given-names>M.</given-names>
   <surname>Kim</surname>
  </string-name>, 
  <string-name>
   <given-names>H.</given-names>
   <surname>Ju</surname>
  </string-name>, 
  <string-name>
   <given-names>J.</given-names>
   <surname>Kim</surname>
  </string-name>, 
  <source xml:lang="en">J. Mater. Chem. A</source>
  <year>2018</year>, 
  <volume>6</volume>, 
  <fpage>8523</fpage>.
 </mixed-citation>
</ref>
