<?xml version="1.0" encoding="UTF-8"?>
<table-wrap id="tbl2" position="float">
 <label>Table 2</label>
 <caption>
  <title>Forty-Eight Other Species Were Predicted to Have an Effective ACE2 Receptor Capable of S-RBD Binding
   <xref rid="tbl2-fn1" ref-type="table-fn">a</xref>
  </title>
 </caption>
 <table frame="hsides" rules="groups" border="0">
  <colgroup>
   <col align="left"/>
   <col align="left"/>
   <col align="left"/>
   <col align="left"/>
  </colgroup>
  <thead>
   <tr>
    <th style="border:none;" align="center">index</th>
    <th style="border:none;" align="center">species</th>
    <th style="border:none;" align="center">animal name</th>
    <th style="border:none;" align="center">binding energy (EEU)</th>
   </tr>
  </thead>
  <tbody>
   <tr>
    <td style="border:none;" align="left">1</td>
    <td style="border:none;" align="left">
     <italic>Pan paniscus</italic>
    </td>
    <td style="border:none;" align="left">Bonobo</td>
    <td style="border:none;" align="left">–55.99 ± 0.12</td>
   </tr>
   <tr>
    <td style="border:none;" align="left">2</td>
    <td style="border:none;" align="left">
     <italic>Nomascus leucogenys</italic>
    </td>
    <td style="border:none;" align="left">Northern white-cheeked gibbon</td>
    <td style="border:none;" align="left">–55.84 ± 0.02</td>
   </tr>
   <tr>
    <td style="border:none;" align="left">3</td>
    <td style="border:none;" align="left">
     <italic>Chlorocebus sabaeus</italic>
    </td>
    <td style="border:none;" align="left">Green monkey</td>
    <td style="border:none;" align="left">–55.67 ± 0.04</td>
   </tr>
   <tr>
    <td style="border:none;" align="left">4</td>
    <td style="border:none;" align="left">
     <italic>Macaca nemestrina</italic>
    </td>
    <td style="border:none;" align="left">Pig-tailed macaque</td>
    <td style="border:none;" align="left">–55.42 ± 0.13</td>
   </tr>
   <tr>
    <td style="border:none;" align="left">5</td>
    <td style="border:none;" align="left">
     <italic>Cercocebus atys</italic>
    </td>
    <td style="border:none;" align="left">Sooty mangabey</td>
    <td style="border:none;" align="left">–55.19 ± 0.01</td>
   </tr>
   <tr>
    <td style="border:none;" align="left">6</td>
    <td style="border:none;" align="left">
     <italic>Mandrillus leucophaeus</italic>
    </td>
    <td style="border:none;" align="left">Drill</td>
    <td style="border:none;" align="left">–54.94 ± 0.22</td>
   </tr>
   <tr>
    <td style="border:none;" align="left">7</td>
    <td style="border:none;" align="left">
     <italic>Nannospalax galili</italic>
    </td>
    <td style="border:none;" align="left">Northern israeli blind subterranean mole rat</td>
    <td style="border:none;" align="left">–53.69 ± 0.18</td>
   </tr>
   <tr>
    <td style="border:none;" align="left">8</td>
    <td style="border:none;" align="left">
     <italic>Propithecus coquereli</italic>
    </td>
    <td style="border:none;" align="left">Coquerel’s sifaka</td>
    <td style="border:none;" align="left">–53.35 ± 0.30</td>
   </tr>
   <tr>
    <td style="border:none;" align="left">9</td>
    <td style="border:none;" align="left">
     <italic>Callorhinus ursinus</italic>
    </td>
    <td style="border:none;" align="left">Northern fur seal</td>
    <td style="border:none;" align="left">–52.98 ± 0.14</td>
   </tr>
   <tr>
    <td style="border:none;" align="left">10</td>
    <td style="border:none;" align="left">
     <italic>Equus przewalskii</italic>
    </td>
    <td style="border:none;" align="left">Mongolian wild horse</td>
    <td style="border:none;" align="left">–52.95 ± 0.34</td>
   </tr>
   <tr>
    <td style="border:none;" align="left">11</td>
    <td style="border:none;" align="left">
     <italic>Acinonyx jubatus</italic>
    </td>
    <td style="border:none;" align="left">Cheetah</td>
    <td style="border:none;" align="left">–52.88 ± 0.92</td>
   </tr>
   <tr>
    <td style="border:none;" align="left">12</td>
    <td style="border:none;" align="left">
     <italic>Heterocephalus glaber</italic>
    </td>
    <td style="border:none;" align="left">Naked mole-rat</td>
    <td style="border:none;" align="left">–52.79 ± 0.04</td>
   </tr>
   <tr>
    <td style="border:none;" align="left">13</td>
    <td style="border:none;" align="left">
     <italic>Bison bison bison</italic>
    </td>
    <td style="border:none;" align="left">Plains bison</td>
    <td style="border:none;" align="left">–52.78 ± 0.08</td>
   </tr>
   <tr>
    <td style="border:none;" align="left">14</td>
    <td style="border:none;" align="left">
     <italic>Mustela erminea</italic>
    </td>
    <td style="border:none;" align="left">Ermine</td>
    <td style="border:none;" align="left">–52.74 ± 0.39</td>
   </tr>
   <tr>
    <td style="border:none;" align="left">15</td>
    <td style="border:none;" align="left">
     <italic>Phoca vitulina</italic>
    </td>
    <td style="border:none;" align="left">Harbor seal</td>
    <td style="border:none;" align="left">–52.73 ± 0.42</td>
   </tr>
   <tr>
    <td style="border:none;" align="left">16</td>
    <td style="border:none;" align="left">
     <italic>Bos indicus x Bos taurus</italic>
    </td>
    <td style="border:none;" align="left">Hybrid cattle</td>
    <td style="border:none;" align="left">–52.71 ± 0.02</td>
   </tr>
   <tr>
    <td style="border:none;" align="left">17</td>
    <td style="border:none;" align="left">
     <italic>Lontra canadensis</italic>
    </td>
    <td style="border:none;" align="left">Northern American river otter</td>
    <td style="border:none;" align="left">–52.66 ± 1.12</td>
   </tr>
   <tr>
    <td style="border:none;" align="left">18</td>
    <td style="border:none;" align="left">
     <italic>Odobenus rosmarus divergens</italic>
    </td>
    <td style="border:none;" align="left">Walrus</td>
    <td style="border:none;" align="left">–52.62 ± 0.53</td>
   </tr>
   <tr>
    <td style="border:none;" align="left">19</td>
    <td style="border:none;" align="left">
     <italic>Bos indicus</italic>
    </td>
    <td style="border:none;" align="left">Zebu cattle</td>
    <td style="border:none;" align="left">–52.47 ± 0.13</td>
   </tr>
   <tr>
    <td style="border:none;" align="left">20</td>
    <td style="border:none;" align="left">
     <italic>Peromyscus maniculatus bairdii</italic>
    </td>
    <td style="border:none;" align="left">Deer mouse</td>
    <td style="border:none;" align="left">–52.38 ± 0.07</td>
   </tr>
   <tr>
    <td style="border:none;" align="left">21</td>
    <td style="border:none;" align="left">
     <italic>Odocoileus virginianus texanus</italic>
    </td>
    <td style="border:none;" align="left">White-tailed deer</td>
    <td style="border:none;" align="left">–52.24 ± 0.67</td>
   </tr>
   <tr>
    <td style="border:none;" align="left">22</td>
    <td style="border:none;" align="left">
     <italic>Fukomys damarensis</italic>
    </td>
    <td style="border:none;" align="left">Damaraland mole-rat</td>
    <td style="border:none;" align="left">–52.22 ± 0.02</td>
   </tr>
   <tr>
    <td style="border:none;" align="left">23</td>
    <td style="border:none;" align="left">
     <italic>Ursus arctos horribilis</italic>
    </td>
    <td style="border:none;" align="left">Grizzly bear</td>
    <td style="border:none;" align="left">–52.13 ± 0.14</td>
   </tr>
   <tr>
    <td style="border:none;" align="left">24</td>
    <td style="border:none;" align="left">
     <italic>Monodon monoceros</italic>
    </td>
    <td style="border:none;" align="left">Narwhal</td>
    <td style="border:none;" align="left">–51.98 ± 0.07</td>
   </tr>
   <tr>
    <td style="border:none;" align="left">25</td>
    <td style="border:none;" align="left">
     <italic>Phocoena sinus</italic>
    </td>
    <td style="border:none;" align="left">Vaquita</td>
    <td style="border:none;" align="left">–51.95 ± 0.05</td>
   </tr>
   <tr>
    <td style="border:none;" align="left">26</td>
    <td style="border:none;" align="left">
     <italic>Microtus ochrogaster</italic>
    </td>
    <td style="border:none;" align="left">Prairie vole</td>
    <td style="border:none;" align="left">–51.76 ± 0.14</td>
   </tr>
   <tr>
    <td style="border:none;" align="left">27</td>
    <td style="border:none;" align="left">
     <italic>Balaenoptera acutorostrata scammoni</italic>
    </td>
    <td style="border:none;" align="left">North pacific minke whale</td>
    <td style="border:none;" align="left">–51.65 ± 0.19</td>
   </tr>
   <tr>
    <td style="border:none;" align="left">28</td>
    <td style="border:none;" align="left">
     <italic>Marmota marmota</italic>
    </td>
    <td style="border:none;" align="left">Alpine marmot</td>
    <td style="border:none;" align="left">–51.62 ± 0.35</td>
   </tr>
   <tr>
    <td style="border:none;" align="left">29</td>
    <td style="border:none;" align="left">
     <italic>Ictidomys tridecemlineatus</italic>
    </td>
    <td style="border:none;" align="left">Thirteen-lined ground squirrel</td>
    <td style="border:none;" align="left">–51.54 ± 0.44</td>
   </tr>
   <tr>
    <td style="border:none;" align="left">30</td>
    <td style="border:none;" align="left">
     <italic>Marmota flaviventris</italic>
    </td>
    <td style="border:none;" align="left">Yellow-bellied marmot</td>
    <td style="border:none;" align="left">–51.50 ± 0.19</td>
   </tr>
   <tr>
    <td style="border:none;" align="left">31</td>
    <td style="border:none;" align="left">
     <italic>Canis lupus dingo</italic>
    </td>
    <td style="border:none;" align="left">Dingo</td>
    <td style="border:none;" align="left">–51.11 ± 0.20</td>
   </tr>
   <tr>
    <td style="border:none;" align="left">32</td>
    <td style="border:none;" align="left">
     <italic>Ochotona princeps</italic>
    </td>
    <td style="border:none;" align="left">American pika</td>
    <td style="border:none;" align="left">–51.01 ± 0.26</td>
   </tr>
   <tr>
    <td style="border:none;" align="left">33</td>
    <td style="border:none;" align="left">
     <italic>Rousettus aegyptiacus</italic>
    </td>
    <td style="border:none;" align="left">Egyptian rousette</td>
    <td style="border:none;" align="left">–50.91 ± 0.48</td>
   </tr>
   <tr>
    <td style="border:none;" align="left">34</td>
    <td style="border:none;" align="left">
     <italic>Lagenorhynchus obliquidens</italic>
    </td>
    <td style="border:none;" align="left">Pacific white-sided dolphin</td>
    <td style="border:none;" align="left">–50.37 ± 0.07</td>
   </tr>
   <tr>
    <td style="border:none;" align="left">35</td>
    <td style="border:none;" align="left">
     <italic>Nyctereutes procyonoides</italic>
    </td>
    <td style="border:none;" align="left">Raccoon dog</td>
    <td style="border:none;" align="left">–50.20 ± 0.79</td>
   </tr>
   <tr>
    <td style="border:none;" align="left">36</td>
    <td style="border:none;" align="left">
     <italic>Equus asinus</italic>
    </td>
    <td style="border:none;" align="left">Donkey</td>
    <td style="border:none;" align="left">–50.02 ± 0.50</td>
   </tr>
   <tr>
    <td style="border:none;" align="left">37</td>
    <td style="border:none;" align="left">
     <italic>Mirounga leonina</italic>
    </td>
    <td style="border:none;" align="left">Southern elephant seal</td>
    <td style="border:none;" align="left">–49.75 ± 0.29</td>
   </tr>
   <tr>
    <td style="border:none;" align="left">38</td>
    <td style="border:none;" align="left">
     <italic>Camelus dromedarius</italic>
    </td>
    <td style="border:none;" align="left">Arabian camel</td>
    <td style="border:none;" align="left">–49.74 ± 0.22</td>
   </tr>
   <tr>
    <td style="border:none;" align="left">39</td>
    <td style="border:none;" align="left">
     <italic>Phyllostomus discolor</italic>
    </td>
    <td style="border:none;" align="left">Pale spear-nosed bat</td>
    <td style="border:none;" align="left">–49.73 ± 0.04</td>
   </tr>
   <tr>
    <td style="border:none;" align="left">40</td>
    <td style="border:none;" align="left">
     <italic>Camelus ferus</italic>
    </td>
    <td style="border:none;" align="left">Wild bactrian camel</td>
    <td style="border:none;" align="left">–49.63 ± 0.12</td>
   </tr>
   <tr>
    <td style="border:none;" align="left">41</td>
    <td style="border:none;" align="left">
     <italic>Pteropus vampyrus</italic>
    </td>
    <td style="border:none;" align="left">Large flying fox</td>
    <td style="border:none;" align="left">–49.29 ± 0.00</td>
   </tr>
   <tr>
    <td style="border:none;" align="left">42</td>
    <td style="border:none;" align="left">
     <italic>Pteropus alecto</italic>
    </td>
    <td style="border:none;" align="left">Black flying fox</td>
    <td style="border:none;" align="left">–49.29 ± 0.06</td>
   </tr>
   <tr>
    <td style="border:none;" align="left">43</td>
    <td style="border:none;" align="left">
     <italic>Dipodomys ordii</italic>
    </td>
    <td style="border:none;" align="left">Ords kangaroo rat</td>
    <td style="border:none;" align="left">–49.01 ± 0.13</td>
   </tr>
   <tr>
    <td style="border:none;" align="left">44</td>
    <td style="border:none;" align="left">
     <italic>Loxodonta africana</italic>
    </td>
    <td style="border:none;" align="left">African savanna elephant</td>
    <td style="border:none;" align="left">–48.80 ± 0.19</td>
   </tr>
   <tr>
    <td style="border:none;" align="left">45</td>
    <td style="border:none;" align="left">
     <italic>Enhydra lutris kenyoni</italic>
    </td>
    <td style="border:none;" align="left">Sea otter</td>
    <td style="border:none;" align="left">–48.53 ± 0.31</td>
   </tr>
   <tr>
    <td style="border:none;" align="left">46</td>
    <td style="border:none;" align="left">
     <italic>Trichechus manatus latirostris</italic>
    </td>
    <td style="border:none;" align="left">Florida manatee</td>
    <td style="border:none;" align="left">–48.13 ± 0.16</td>
   </tr>
   <tr>
    <td style="border:none;" align="left">47</td>
    <td style="border:none;" align="left">
     <italic>Octodon degus</italic>
    </td>
    <td style="border:none;" align="left">Common degu</td>
    <td style="border:none;" align="left">–47.70 ± 0.13</td>
   </tr>
   <tr>
    <td style="border:none;" align="left">48</td>
    <td style="border:none;" align="left">
     <italic>Vicugna pacos</italic>
    </td>
    <td style="border:none;" align="left">Alpaca</td>
    <td style="border:none;" align="left">–47.11 ± 0.07</td>
   </tr>
  </tbody>
 </table>
 <table-wrap-foot>
  <fn id="tbl2-fn1">
   <label>a</label>
   <p>The table is organized by ranking the binding energy from low to high. The species in 
    <xref rid="tbl1" ref-type="other">Table 
     <xref rid="tbl1" ref-type="other">1</xref>
    </xref> were not included in this table. The binding energy cutoff (−47 EEU) was chosen by maximally discriminating the experimentally determined effective ACE2 receptors from the less effective ones.
   </p>
  </fn>
 </table-wrap-foot>
</table-wrap>
