<?xml version="1.0" encoding="UTF-8"?>
<ref id="cit0173">
 <label>[173]</label>
 <mixed-citation publication-type="journal">
  <person-group person-group-type="author">
   <string-name>
    <surname>Kornspan</surname>
    <given-names>J-D</given-names>
   </string-name>, 
   <string-name>
    <surname>Tarshis</surname>
    <given-names>M</given-names>
   </string-name>
  </person-group>, Rottem S. Adhesion and biofilm formation of 
  <italic>Mycoplasma pneumoniae</italic> on an abiotic surface. Archives of Microbiology. 
  <year>2011</year>;
  <volume>193</volume>(
  <issue>11</issue>):
  <fpage>833</fpage>–
  <lpage>836</lpage>.
 </mixed-citation>
</ref>
