<?xml version="1.0" encoding="UTF-8"?>
<fig id="fig6">
 <label>Figure 6</label>
 <caption>
  <p>Radar-charts of 15 differential DNA repair pathway activation profile for (A) follicular adenoma, ANTE normal samples used for PAL calculation, (B) follicular adenoma, GTEx normal samples used for PAL calculation, (C) follicular adenoma, TCGA normal samples used for PAL calculation, (D) follicular cancer, ANTE normal samples used for PAL calculation, (E) follicular cancer, CTEx normal samples used for PAL calculation, (F) follicular cancer, TCGA normal samples used for PAL calculation, (G) papillary cancer, ANTE normal samples used for PAL calculation, (H) papillary cancer, GTEx normal samples used for PAL calculation, (I) papillary cancer, TCGA normal samples used for PAL calculation. Positive pathway activation values (PALs) are shown in the outer white area, negative values –in the inner red circle area.</p>
 </caption>
 <alt-text id="alttext0080">Figure 6</alt-text>
 <graphic xlink:href="gr6" xmlns:xlink="http://www.w3.org/1999/xlink"/>
</fig>
