<?xml version="1.0" encoding="UTF-8"?>
<fig id="materials-12-04083-f045" orientation="portrait" position="float">
 <label>Figure 45</label>
 <caption>
  <p>Fine quench-induced hexagonal β′-Mg
   <sub>9</sub>Si
   <sub>5</sub> particles after cooling Al0.6Mg0.8Si at 0.1 K/s. The β′-particles apparently contain disordered areas (TEM work by Shravan Kairy and Matthew Weyland, Monash University, Melbourne, Australia).
  </p>
 </caption>
 <graphic xlink:href="materials-12-04083-g045" xmlns:xlink="http://www.w3.org/1999/xlink"/>
</fig>
