<?xml version="1.0" encoding="UTF-8"?>
<funding-group>
 <award-group>
  <funding-source>
   <institution-wrap>
    <institution-id institution-id-type="FundRef">http://dx.doi.org/10.13039/100007868</institution-id>
    <institution>Columbus Zoo and Aquarium</institution>
   </institution-wrap>
  </funding-source>
  <award-id>6000194</award-id>
  <award-id>6000194</award-id>
  <principal-award-recipient>
   <name>
    <surname>Roznere</surname>
    <given-names>Ieva</given-names>
   </name>
   <name>
    <surname>Watters</surname>
    <given-names>G. Thomas</given-names>
   </name>
  </principal-award-recipient>
 </award-group>
</funding-group>
