<?xml version="1.0" encoding="UTF-8"?>
<fig id="Fig4">
 <label>Figure 4</label>
 <caption>
  <p>The results of Gene ontology and pathway analysis. (
   <bold>A</bold>) Gene ontology and pathway related to muscle development. (
   <bold>B</bold>) Gene expression in Gene ontology and pathway related to muscle development, the bar code represents the color scale of the log
   <sub>10</sub>
   <sup>(FC)</sup>.
  </p>
 </caption>
 <graphic xlink:href="41598_2021_82126_Fig4_HTML" id="MO4" xmlns:xlink="http://www.w3.org/1999/xlink"/>
</fig>
