<?xml version="1.0" encoding="UTF-8"?>
<disp-formula id="E2">
 <label>(2)</label>
 <math id="M4">
  <mtable class="eqnarray" columnalign="left">
   <mtr>
    <mtd>
     <mtext>Mo</mtext>
     <msub>
      <mrow>
       <mtext>S</mtext>
      </mrow>
      <mrow>
       <mn>2</mn>
      </mrow>
     </msub>
     <mo>+</mo>
     <mtext>xL</mtext>
     <msup>
      <mrow>
       <mtext>i</mtext>
      </mrow>
      <mrow>
       <mo>+</mo>
      </mrow>
     </msup>
     <mo>+</mo>
     <mtext>x</mtext>
     <msup>
      <mrow>
       <mtext>e</mtext>
      </mrow>
      <mrow>
       <mo>-</mo>
      </mrow>
     </msup>
    </mtd>
    <mtd>
     <mo>→</mo>
    </mtd>
    <mtd>
     <mtext>L</mtext>
     <msub>
      <mrow>
       <mtext>i</mtext>
      </mrow>
      <mrow>
       <mtext>x</mtext>
      </mrow>
     </msub>
     <mtext>Mo</mtext>
     <msub>
      <mrow>
       <mtext>S</mtext>
      </mrow>
      <mrow>
       <mn>2</mn>
      </mrow>
     </msub>
    </mtd>
   </mtr>
  </mtable>
 </math>
</disp-formula>
