<?xml version="1.0" encoding="UTF-8"?>
<ref id="advs1507-bib-0020">
 <label>20</label>
 <mixed-citation publication-type="journal" id="advs1507-cit-0032">
  <string-name>
   <given-names>Q.</given-names>
   <surname>Guo</surname>
  </string-name>, 
  <string-name>
   <given-names>Y.</given-names>
   <surname>Han</surname>
  </string-name>, 
  <string-name>
   <given-names>H.</given-names>
   <surname>Wang</surname>
  </string-name>, 
  <string-name>
   <given-names>S.</given-names>
   <surname>Xiong</surname>
  </string-name>, 
  <string-name>
   <given-names>Y.</given-names>
   <surname>Li</surname>
  </string-name>, 
  <string-name>
   <given-names>S.</given-names>
   <surname>Liu</surname>
  </string-name>, 
  <string-name>
   <given-names>K.</given-names>
   <surname>Xie</surname>
  </string-name>, 
  <source xml:lang="en">ACS Appl. Mater. Interfaces</source>
  <year>2017</year>, 
  <volume>9</volume>, 
  <elocation-id>41837</elocation-id>.
  <pub-id pub-id-type="pmid">29131566</pub-id>
 </mixed-citation>
</ref>
