<?xml version="1.0" encoding="UTF-8"?>
<ref id="advs1507-bib-0080">
 <label>80</label>
 <mixed-citation publication-type="journal" id="advs1507-cit-0104">
  <string-name>
   <given-names>S.</given-names>
   <surname>Zekoll</surname>
  </string-name>, 
  <string-name>
   <given-names>C.</given-names>
   <surname>Marriner‐Edwards</surname>
  </string-name>, 
  <string-name>
   <given-names>A. K. O.</given-names>
   <surname>Hekselman</surname>
  </string-name>, 
  <string-name>
   <given-names>J.</given-names>
   <surname>Kasemchainan</surname>
  </string-name>, 
  <string-name>
   <given-names>C.</given-names>
   <surname>Kuss</surname>
  </string-name>, 
  <string-name>
   <given-names>D. E. J.</given-names>
   <surname>Armstrong</surname>
  </string-name>, 
  <string-name>
   <given-names>D.</given-names>
   <surname>Cai</surname>
  </string-name>, 
  <string-name>
   <given-names>R. J.</given-names>
   <surname>Wallace</surname>
  </string-name>, 
  <string-name>
   <given-names>F. H.</given-names>
   <surname>Richter</surname>
  </string-name>, 
  <string-name>
   <given-names>J. H. J.</given-names>
   <surname>Thijssen</surname>
  </string-name>, 
  <string-name>
   <given-names>P. G.</given-names>
   <surname>Bruce</surname>
  </string-name>, 
  <source xml:lang="en">Energy Environ. Sci.</source>
  <year>2018</year>, 
  <volume>11</volume>, 
  <fpage>185</fpage>.
 </mixed-citation>
</ref>
