<?xml version="1.0" encoding="UTF-8"?>
<fig id="F5" position="float">
 <label>FIGURE 5</label>
 <caption>
  <p>CPSF1 knockdown induced differential expression of transcripts. 
   <bold>(A)</bold> A volcano plot illustrates the expression of transcripts following the silencing CPSF1 in HepG2.2.15 cells. Up- and downregulated transcripts are highlighted as red and blue dots, respectively. Barplots showing the top 10 significantly enriched KEGG pathways 
   <bold>(B)</bold> and GO biological processes 
   <bold>(C)</bold> identified by the gene set analysis using DAVID. 
   <bold>(D)</bold> List of top 10 representative genes down- or upregulated following CPSF1 silencing is presented.
  </p>
 </caption>
 <graphic xlink:href="fcell-09-616835-g005" xmlns:xlink="http://www.w3.org/1999/xlink"/>
</fig>
