<?xml version="1.0" encoding="UTF-8"?>
<contrib-group>
 <contrib id="author-79448298" contrib-type="author">
  <name>
   <surname>Merola</surname>
   <given-names>Joseph F</given-names>
  </name>
  <xref ref-type="aff" rid="aff1">1</xref>
  <xref ref-type="aff" rid="aff2">2</xref>
 </contrib>
 <contrib id="author-79448393" contrib-type="author">
  <name>
   <surname>Wang</surname>
   <given-names>Wenting</given-names>
  </name>
  <xref ref-type="aff" rid="aff3">3</xref>
 </contrib>
 <contrib id="author-79448697" contrib-type="author">
  <name>
   <surname>Wager</surname>
   <given-names>Carrie G</given-names>
  </name>
  <xref ref-type="aff" rid="aff3">3</xref>
 </contrib>
 <contrib id="author-79448775" contrib-type="author">
  <name>
   <surname>Hamann</surname>
   <given-names>Stefan</given-names>
  </name>
  <xref ref-type="aff" rid="aff3">3</xref>
 </contrib>
 <contrib id="author-79448854" contrib-type="author">
  <name>
   <surname>Zhang</surname>
   <given-names>Xueli</given-names>
  </name>
  <xref ref-type="aff" rid="aff3">3</xref>
 </contrib>
 <contrib id="author-79448906" contrib-type="author">
  <name>
   <surname>Thai</surname>
   <given-names>Alice</given-names>
  </name>
  <xref ref-type="aff" rid="aff3">3</xref>
 </contrib>
 <contrib id="author-79448961" contrib-type="author">
  <name>
   <surname>Roberts</surname>
   <given-names>Christopher</given-names>
  </name>
  <xref ref-type="aff" rid="aff3">3</xref>
 </contrib>
 <contrib id="author-58299827" contrib-type="author">
  <name>
   <surname>Lam</surname>
   <given-names>Christina</given-names>
  </name>
  <xref ref-type="aff" rid="aff4">4</xref>
 </contrib>
 <contrib id="author-79449153" contrib-type="author">
  <name>
   <surname>Musselli</surname>
   <given-names>Cristina</given-names>
  </name>
  <xref ref-type="aff" rid="aff3">3</xref>
 </contrib>
 <contrib id="author-79449289" contrib-type="author">
  <name>
   <surname>Marsh</surname>
   <given-names>Galina</given-names>
  </name>
  <xref ref-type="aff" rid="aff3">3</xref>
 </contrib>
 <contrib id="author-79449337" contrib-type="author">
  <name>
   <surname>Rabah</surname>
   <given-names>Dania</given-names>
  </name>
  <xref ref-type="aff" rid="aff3">3</xref>
 </contrib>
 <contrib id="author-79449477" contrib-type="author">
  <name>
   <surname>Barbey</surname>
   <given-names>Catherine</given-names>
  </name>
  <xref ref-type="aff" rid="aff5">5</xref>
 </contrib>
 <contrib id="author-79449556" contrib-type="author">
  <name>
   <surname>Franchimont</surname>
   <given-names>Nathalie</given-names>
  </name>
  <xref ref-type="aff" rid="aff3">3</xref>
 </contrib>
 <contrib id="author-79363185" contrib-type="author" corresp="yes">
  <contrib-id contrib-id-type="orcid" authenticated="false">http://orcid.org/0000-0002-6941-0900</contrib-id>
  <name>
   <surname>Reynolds</surname>
   <given-names>Taylor L</given-names>
  </name>
  <xref ref-type="aff" rid="aff3">3</xref>
 </contrib>
</contrib-group>
