<?xml version="1.0" encoding="UTF-8"?>
<fig id="pone.0246818.g016" orientation="portrait" position="float">
 <object-id pub-id-type="doi">10.1371/journal.pone.0246818.g016</object-id>
 <label>Fig 16</label>
 <caption>
  <title>Go enrichment of the transcriptional up-regulated genes in 
   <italic>S</italic>. 
   <italic>pasteurii</italic> between groups of N and U.
  </title>
  <p>The x-axis represents the ratio of the number of differential genes annotated to the pathway number to the total number of differential genes. The y-axis represents the name of the enriched pathway.</p>
 </caption>
 <graphic xlink:href="pone.0246818.g016" xmlns:xlink="http://www.w3.org/1999/xlink"/>
</fig>
